{
  "version": 2,
  "extractor": "pdffigures2",
  "figures": [
    {
      "url": "assets/figures/arxiv/2603.24800v1/fig-001.webp",
      "caption": "Figure 6. Comparison between Calibri Ensemble and original model across several inference steps.",
      "page": 6,
      "index": 1,
      "width": 464,
      "height": 283
    },
    {
      "url": "assets/figures/arxiv/2603.24800v1/fig-002.webp",
      "caption": "Figure 9. Limitations of modern reward models.",
      "page": 11,
      "index": 2,
      "width": 469,
      "height": 341
    },
    {
      "url": "assets/figures/arxiv/2603.24800v1/fig-003.webp",
      "caption": "Figure 7. Qualitative evaluation of generation quality improvements across various baseline models. Models have same NFE as in Table 2.",
      "page": 7,
      "index": 3,
      "width": 1036,
      "height": 1037
    },
    {
      "url": "assets/figures/arxiv/2603.24800v1/fig-004.webp",
      "caption": "Figure 2. Illustration of DiT architectural components.",
      "page": 3,
      "index": 4,
      "width": 491,
      "height": 307
    },
    {
      "url": "assets/figures/arxiv/2603.24800v1/fig-005.webp",
      "caption": "Figure 3. Motivational Experiment: Our findings reveal that the contribution of DiT blocks is not fully optimized. We demonstrate that their performance can be enhanced through a straightforward output scaling using a scalar multiplier.",
      "page": 3,
      "index": 5,
      "width": 485,
      "height": 707
    },
    {
      "url": "assets/figures/arxiv/2603.24800v1/fig-006.webp",
      "caption": "Figure 12. CMA-ES algorithm optimizes Calibri coefficients for layer scale FLUX.",
      "page": 13,
      "index": 6,
      "width": 495,
      "height": 746
    },
    {
      "url": "assets/figures/arxiv/2603.24800v1/fig-007.webp",
      "caption": "Figure 8. Qualitative comparison of Calibri and Flow-GRPO [24] on SD-3.5M. Calibri achieves comparable performance with 105 fewer parameters and can be combined with alignment methods to boost either the same or different target metrics.",
      "page": 8,
      "index": 7,
      "width": 1027,
      "height": 594
    },
    {
      "url": "assets/figures/arxiv/2603.24800v1/fig-008.webp",
      "caption": "Figure 4. Illustration of calibration parameter search procedure.",
      "page": 4,
      "index": 8,
      "width": 1006,
      "height": 219
    },
    {
      "url": "assets/figures/arxiv/2603.24800v1/fig-009.webp",
      "caption": "Figure 11. Comparison of CMA-ES and Flow-GRPO performance in optimizing Calibri coefficients.",
      "page": 12,
      "index": 9,
      "width": 465,
      "height": 305
    },
    {
      "url": "assets/figures/arxiv/2603.24800v1/fig-010.webp",
      "caption": "Figure 10. Illustration of Calibri with different rewards as objective.",
      "page": 12,
      "index": 10,
      "width": 479,
      "height": 469
    }
  ]
}