{
  "version": 2,
  "extractor": "pdffigures2",
  "figures": [
    {
      "url": "assets/figures/arxiv/2605.10095v1/fig-001.webp",
      "caption": "Fig. 6. Distributions of PSNR (a–d) and MS-SSIM (e–h) for reconstructed images. (a)–(d) show PSNR for rl_dqn, max_rate, mid_rate, and min_rate, respectively; (e)–(h) show the MS-SSIM distributions for the same four methods.",
      "page": 10,
      "index": 1,
      "width": 1060,
      "height": 388
    },
    {
      "url": "assets/figures/arxiv/2605.10095v1/fig-002.webp",
      "caption": "Fig. 7. Comparison of reconstruction quality for the lowest-PSNR image per policy. Left: original; right: reconstructed.",
      "page": 10,
      "index": 2,
      "width": 500,
      "height": 857
    },
    {
      "url": "assets/figures/arxiv/2605.10095v1/fig-003.webp",
      "caption": "Fig. 5. Process of SNR sweep and adjust of target rate at ΓPSNR = 32 dB and ΓMS-SSIM = 0.94.",
      "page": 9,
      "index": 3,
      "width": 450,
      "height": 961
    }
  ]
}