{
  "version": 2,
  "extractor": "pdffigures2",
  "figures": [
    {
      "url": "assets/figures/arxiv/2603.21233v1/fig-001.webp",
      "caption": "Table 2: Performance comparison with standard image codecs on the DIODE [29] dataset. Our method achieves a competitive accuracy comparable to the near-lossless JPEG-LS but at a significantly reduced bitrate.",
      "page": 15,
      "index": 1,
      "width": 806,
      "height": 183
    },
    {
      "url": "assets/figures/arxiv/2603.21233v1/fig-002.webp",
      "caption": "Figure 2: Visualization of Multiwavelength Depth Encoding. (a) Input 32-bit depth map, (b) 8-bit Quantized MWD Encoded Map, (c) 4-bit Quantized MWD Encoded Map, (d) Red channel: sinusoidal encoding, sin(2πZ/P ). (e) Green channel: sinusoidal encoding, cos(2πZ/P ), (f) Blue channel: normalized depth for long-wavelength variation.",
      "page": 10,
      "index": 2,
      "width": 814,
      "height": 406
    },
    {
      "url": "assets/figures/arxiv/2603.21233v1/fig-003.webp",
      "caption": "Figure 3: Rate–distortion curves on the Middlebury 2014 dataset. NRMSE (%) is plotted against bitrate (bpp) measured per original depth pixel. The error is computed following the evaluation protocol of N-DEPTH, where metrics are calculated over the shared intersection of valid recovery regions. Rate–distortion operating points of our method are obtained by varying the Lagrangian multiplier λ.",
      "page": 14,
      "index": 3,
      "width": 814,
      "height": 387
    },
    {
      "url": "assets/figures/arxiv/2603.21233v1/fig-004.webp",
      "caption": "Table 7: Average inference time (Ours, 4-bit) at benchmark input depth resolutions. Throughput is 1000/t (FPS).",
      "page": 18,
      "index": 4,
      "width": 804,
      "height": 205
    },
    {
      "url": "assets/figures/arxiv/2603.21233v1/fig-005.webp",
      "caption": "Table 8: Ablation study of quantization bit-depths on the DIODE dataset.",
      "page": 18,
      "index": 5,
      "width": 744,
      "height": 287
    },
    {
      "url": "assets/figures/arxiv/2603.21233v1/fig-006.webp",
      "caption": "Figure 1: DepthTCM framework architecture. The framework integrates multiwavelength depth (MWD) encoding, 4-bit quantization, and a hybrid Transformer–CNN compression backbone into a fully differentiable end-to-end system for efficient depth map compression and reconstruction.",
      "page": 4,
      "index": 6,
      "width": 814,
      "height": 544
    },
    {
      "url": "assets/figures/arxiv/2603.21233v1/fig-007.webp",
      "caption": "Table 11: Comparison between our MWD-based approach and the standalone TCM backbone (Only-TCM) on the DIODE dataset. The “Only-TCM” baseline fails to capture geometric structures, resulting in high bitrates and low PSNR compared to our method.",
      "page": 20,
      "index": 7,
      "width": 812,
      "height": 413
    }
  ]
}