{
  "version": 2,
  "extractor": "pdffigures2",
  "figures": [
    {
      "url": "assets/figures/arxiv/2605.01355v1/fig-001.webp",
      "caption": "Table 6: Baseline model performance across all three datasets without imbalance handling. Best result per dataset shown in bold.",
      "page": 25,
      "index": 1,
      "width": 814,
      "height": 245
    },
    {
      "url": "assets/figures/arxiv/2605.01355v1/fig-002.webp",
      "caption": "Figure 13: Grad-CAM on Potato dataset",
      "page": 38,
      "index": 2,
      "width": 842,
      "height": 471
    },
    {
      "url": "assets/figures/arxiv/2605.01355v1/fig-003.webp",
      "caption": "Figure 4: Projection 2: Group-wise Linear (GWL) projector for matching grouped student spatial features to teacher token representations.",
      "page": 15,
      "index": 3,
      "width": 652,
      "height": 489
    },
    {
      "url": "assets/figures/arxiv/2605.01355v1/fig-004.webp",
      "caption": "Figure 7: Burmese Grape Leaf Disease dataset overview.",
      "page": 21,
      "index": 4,
      "width": 772,
      "height": 610
    },
    {
      "url": "assets/figures/arxiv/2605.01355v1/fig-005.webp",
      "caption": "Figure 9: Accuracy comparison between teacher and distilled student across the three datasets.",
      "page": 30,
      "index": 5,
      "width": 895,
      "height": 673
    },
    {
      "url": "assets/figures/arxiv/2605.01355v1/fig-006.webp",
      "caption": "Figure 14: Performance comparison of existing approaches on the Potato Leaf Disease dataset",
      "page": 39,
      "index": 6,
      "width": 814,
      "height": 346
    },
    {
      "url": "assets/figures/arxiv/2605.01355v1/fig-007.webp",
      "caption": "Figure 8: Representative samples from each class in the Potato Leaf Disease dataset.",
      "page": 22,
      "index": 7,
      "width": 814,
      "height": 860
    },
    {
      "url": "assets/figures/arxiv/2605.01355v1/fig-008.webp",
      "caption": "Table 14: Cross-format deployment evaluation across datasets",
      "page": 42,
      "index": 8,
      "width": 814,
      "height": 368
    },
    {
      "url": "assets/figures/arxiv/2605.01355v1/fig-009.webp",
      "caption": "Table 13: Ablation study on the Potato Leaf Disease dataset",
      "page": 33,
      "index": 9,
      "width": 814,
      "height": 225
    },
    {
      "url": "assets/figures/arxiv/2605.01355v1/fig-010.webp",
      "caption": "Table 12: Ablation study on the Tomato Leaf Disease dataset",
      "page": 33,
      "index": 10,
      "width": 814,
      "height": 227
    },
    {
      "url": "assets/figures/arxiv/2605.01355v1/fig-011.webp",
      "caption": "Table 1: Class distribution of the Tomato Leaf Disease dataset.",
      "page": 18,
      "index": 11,
      "width": 412,
      "height": 306
    },
    {
      "url": "assets/figures/arxiv/2605.01355v1/fig-012.webp",
      "caption": "Table 4: Hyperparameter configuration for baseline models on Tomato, Burmese Grape, and Potato datasets",
      "page": 23,
      "index": 12,
      "width": 814,
      "height": 325
    },
    {
      "url": "assets/figures/arxiv/2605.01355v1/fig-013.webp",
      "caption": "Figure 3: Projection 1: Partially Cross-Attention (PCA) projector for aligning student convolutional features with teacher attention representations.",
      "page": 13,
      "index": 13,
      "width": 798,
      "height": 600
    },
    {
      "url": "assets/figures/arxiv/2605.01355v1/fig-014.webp",
      "caption": "Figure 1: Overview of the proposed AgriKD framework: a pre-trained ViT-Base teacher distills knowledge into a truncated MobileNetV2 student via multi-component distillation",
      "page": 8,
      "index": 14,
      "width": 1085,
      "height": 814
    },
    {
      "url": "assets/figures/arxiv/2605.01355v1/fig-015.webp",
      "caption": "Figure 15: Inference on NVIDIA Jetson Orin Nano using TensorRT FP16: Potato datasets.",
      "page": 40,
      "index": 15,
      "width": 814,
      "height": 466
    },
    {
      "url": "assets/figures/arxiv/2605.01355v1/fig-016.webp",
      "caption": "Figure 11: Grad-CAM on Burmese Grape dataset",
      "page": 36,
      "index": 16,
      "width": 869,
      "height": 471
    },
    {
      "url": "assets/figures/arxiv/2605.01355v1/fig-017.webp",
      "caption": "Figure 5: Representative samples from each class in the Tomato Leaf Disease dataset.",
      "page": 19,
      "index": 17,
      "width": 610,
      "height": 460
    },
    {
      "url": "assets/figures/arxiv/2605.01355v1/fig-018.webp",
      "caption": "Table 11: Model efficiency comparison: ViT-Base teacher versus distilled student across datasets",
      "page": 32,
      "index": 18,
      "width": 814,
      "height": 198
    },
    {
      "url": "assets/figures/arxiv/2605.01355v1/fig-019.webp",
      "caption": "Figure 2: Illustration of the relation-based distillation component. The loss preserves structural agreement between teacher and student predictions through inter-instance and inter-class correlation matching.",
      "page": 12,
      "index": 19,
      "width": 668,
      "height": 502
    },
    {
      "url": "assets/figures/arxiv/2605.01355v1/fig-020.webp",
      "caption": "Figure 16: Mobile application using TFLite Float16: application menu (left), Tomato inference (center), and Potato inference (right).",
      "page": 41,
      "index": 20,
      "width": 798,
      "height": 581
    },
    {
      "url": "assets/figures/arxiv/2605.01355v1/fig-021.webp",
      "caption": "Figure 12: Grad-CAM on Tomato dataset",
      "page": 37,
      "index": 21,
      "width": 846,
      "height": 471
    }
  ]
}